setup.py
tarpies.py
tarpies.egg-info/PKG-INFO
tarpies.egg-info/SOURCES.txt
tarpies.egg-info/dependency_links.txt
tarpies.egg-info/top_level.txt